novabot_plugin_picsearcher_adv/ASCII2D.py
novabot_plugin_picsearcher_adv/SauceNAO.py
novabot_plugin_picsearcher_adv/Soutubot.py
novabot_plugin_picsearcher_adv/TraceMoe.py
novabot_plugin_picsearcher_adv/__init__.py
novabot_plugin_picsearcher_adv/cache.py
novabot_plugin_picsearcher_adv/config.py
novabot_plugin_picsearcher_adv/iqdb.py
novabot_plugin_picsearcher_adv/utils.py
novabot_plugin_picsearcher_adv-0.1.2.dist-info/LICENSE
novabot_plugin_picsearcher_adv-0.1.2.dist-info/WHEEL
novabot_plugin_picsearcher_adv-0.1.2.dist-info/METADATA
novabot_plugin_picsearcher_adv-0.1.2.dist-info/RECORD
