Metadata-Version: 2.1
Name: novabot-plugin-picsearcher-adv
Version: 0.1.2
Summary: Nova-Bot plugin help you to find the source of (Anime) Images.
Author: NovaNo1r
Author-email: mail@novanoir.dev
Requires-Python: >=3.10,<4.0
Classifier: Programming Language :: Python :: 3
Classifier: Programming Language :: Python :: 3.10
Requires-Dist: beautifulsoup4 (>=4.11.1,<5.0.0)
Requires-Dist: diskcache (>=5.4.0,<6.0.0)
Requires-Dist: lxml (>=4.9.1,<5.0.0)
Requires-Dist: picimagesearch (>=3.3.11,<4.0.0)
